demos/__init__.py
hagike/__init__.py
hagike/basics/__init__.py
hagike/basics/cv/__init__.py
hagike/basics/cv/filter.py
hagike/basics/cv/histogram.py
hagike/basics/cv/noise.py
hagike/basics/cv/transform.py
hagike/basics/cv/file/__init__.py
hagike/basics/cv/file/image/__init__.py
hagike/basics/cv/file/image/const.py
hagike/basics/cv/file/image/error.py
hagike/basics/cv/file/image/func.py
hagike/basics/cv/file/image/im.py
hagike/log/__init__.py
hagike/log/const.py
hagike/log/logger.py
hagike/models/__init__.py
hagike/models/cv/__init__.py
hagike/models/deploy/__init__.py
hagike/models/nlp/__init__.py
hagike/models/rl/__init__.py
hagike/models/temp/__init__.py
hagike/models/temp/common.py
hagike/models/temp/const.py
hagike/models/temp/error.py
hagike/models/temp/model.py
hagike/models/temp/module.py
hagike/models/temp/node.py
hagike/models/temp/unit.py
hagike/models/train/__init__.py
hagike/models/train/const.py
hagike/models/train/criterion.py
hagike/models/train/dataloader.py
hagike/models/train/error.py
hagike/models/train/evaluator.py
hagike/models/train/monitor.py
hagike/models/train/optimizer.py
hagike/models/train/trainer.py
hagike/models/train/dataset/__init__.py
hagike/models/train/dataset/dataset.py
hagike/models/train/dataset/tcv.py
hagike/system/__init__.py
hagike/system/core/__init__.py
hagike/system/interface/__init__.py
hagike/tools/__init__.py
hagike/tools/matlab/__init__.py
hagike/tools/matlab/utils.py
hagike/tools/matlab/engine/__init__.py
hagike/tools/matlab/engine/const.py
hagike/tools/matlab/engine/engine.py
hagike/tools/matlab/engine/error.py
hagike/tools/matlab/scripts/__init__.py
hagike/tools/matlab/scripts/m_feval.m
hagike/tools/matlab/scripts/m_operator.m
hagike/tools/matlab/system/__init__.py
hagike/tools/matlab/system/const.py
hagike/tools/matlab/system/error.py
hagike/tools/matlab/system/sys.py
hagike/utils/__init__.py
hagike/utils/abort.py
hagike/utils/cache.py
hagike/utils/config.py
hagike/utils/enum.py
hagike/utils/file.py
hagike-0.0.7.dist-info/LICENSE
hagike-0.0.7.dist-info/METADATA
hagike-0.0.7.dist-info/WHEEL
hagike-0.0.7.dist-info/top_level.txt
hagike-0.0.7.dist-info/RECORD
