Metadata-Version: 2.1
Name: hagike
Version: 0.0.7
Summary: hagike toolkit for everything
Author: hagikehappy
Author-email: hagikehappy@163.com
Project-URL: Homepage, https://github.com/hagikehappy/hagike
Project-URL: Issues, https://github.com/hagikehappy/hagike/issues
Classifier: Programming Language :: Python :: 3
Classifier: License :: OSI Approved :: GNU Lesser General Public License v3 (LGPLv3)
Classifier: Operating System :: OS Independent
Requires-Python: >=3.10
License-File: LICENSE
